MANIFEST.in
README.md
setup.py
pypipedrive/__init__.py
pypipedrive/api.py
pypipedrive.egg-info/PKG-INFO
pypipedrive.egg-info/SOURCES.txt
pypipedrive.egg-info/dependency_links.txt
pypipedrive.egg-info/requires.txt
pypipedrive.egg-info/top_level.txt