Metadata-Version: 1.1
Name: pypipedrive
Version: 0.1.1
Summary: Python wrapper for the Pipedrive API
Home-page: https://github.com/42cc/pypipedrive
Author: Andriy Sheerpa
Author-email: asherepa@gmail.com
License: BSD License
Download-URL: https://github.com/42cc/pypipedrive/tarball/master
Keywords: pipedrive,api
Platform: UNKNOWN
Classifier: Environment :: Web Environment
Classifier: Intended Audience :: Developers
Classifier: License :: OSI Approved :: BSD License
Classifier: Programming Language :: Python
Requires: python (>= 2.7)
Requires: requests
